README.rst
setup.py
tabkit/__init__.py
tabkit/exception.py
tabkit/header.py
tabkit/scripts.py
tabkit/type.py
tabkit/utils.py
tabkit.egg-info/PKG-INFO
tabkit.egg-info/SOURCES.txt
tabkit.egg-info/dependency_links.txt
tabkit.egg-info/entry_points.txt
tabkit.egg-info/top_level.txt
tabkit/awk/__init__.py
tabkit/awk/group.py
tabkit/awk/map.py