Metadata-Version: 1.0
Name: tabkit
Version: 0.11
Summary: Coreutils-like kit for headed tab-separated files processing
Home-page: https://github.com/andreifyodorov/tabkit
Author: Andrei Fyodorov
Author-email: sour-times@yandex.ru
License: PSF
Platform: UNKNOWN
